MANIFEST.in
README.rst
requirements.txt
setup.py
botsocket/__init__.py
botsocket/client.py
botsocket/commandbus.py
botsocket/exceptions.py
botsocket/server.py
botsocket.egg-info/PKG-INFO
botsocket.egg-info/SOURCES.txt
botsocket.egg-info/dependency_links.txt
botsocket.egg-info/requires.txt
botsocket.egg-info/top_level.txt