Metadata-Version: 1.0
Name: botsocket
Version: 0.2.3
Summary: socket server for bot communication
Home-page: https://github.com/ostrbor/botsocket
Author: Boris Ostretsov
Author-email: ostrbor@gmail.com
License: MIT
Keywords: bot botnet socket server
Platform: UNKNOWN
